{
"meta":{"test_sets":[],"test_metrics":[],"learn_metrics":[{"best_value":"Min","name":"RMSE"}],"launch_mode":"Train","parameters":"","iteration_count":322,"learn_sets":["learn"],"name":"experiment"},
"iterations":[
{"learn":[0.4952916763],"iteration":0,"passed_time":0.002527796049,"remaining_time":0.8114225316},
{"learn":[0.4912065272],"iteration":1,"passed_time":0.004376136221,"remaining_time":0.7001817953},
{"learn":[0.4873687227],"iteration":2,"passed_time":0.006183519015,"remaining_time":0.6575141886},
{"learn":[0.4833406513],"iteration":3,"passed_time":0.008901889899,"remaining_time":0.707700247},
{"learn":[0.4794304706],"iteration":4,"passed_time":0.01068080594,"remaining_time":0.6771630963},
{"learn":[0.47576623],"iteration":5,"passed_time":0.01237558106,"remaining_time":0.6517806027},
{"learn":[0.4720879388],"iteration":6,"passed_time":0.01419828927,"remaining_time":0.6389230173},
{"learn":[0.4683047035],"iteration":7,"passed_time":0.01620339716,"remaining_time":0.6359833385},
{"learn":[0.4649078256],"iteration":8,"passed_time":0.01788792586,"remaining_time":0.6221023104},
{"learn":[0.4618412607],"iteration":9,"passed_time":0.01960024998,"remaining_time":0.6115277993},
{"learn":[0.4590314836],"iteration":10,"passed_time":0.02128877665,"remaining_time":0.6018917761},
{"learn":[0.455947823],"iteration":11,"passed_time":0.0229484057,"remaining_time":0.592833814},
{"learn":[0.4529044498],"iteration":12,"passed_time":0.02579700538,"remaining_time":0.6131749741},
{"learn":[0.4498815067],"iteration":13,"passed_time":0.02776728154,"remaining_time":0.6108801938},
{"learn":[0.4470329175],"iteration":14,"passed_time":0.03021305032,"remaining_time":0.6183604299},
{"learn":[0.4446337501],"iteration":15,"passed_time":0.03202566526,"remaining_time":0.6124908481},
{"learn":[0.4420799429],"iteration":16,"passed_time":0.03374814878,"remaining_time":0.6054814928},
{"learn":[0.4397118285],"iteration":17,"passed_time":0.03548400582,"remaining_time":0.5992854316},
{"learn":[0.4373061813],"iteration":18,"passed_time":0.03723261228,"remaining_time":0.5937621853},
{"learn":[0.4350212402],"iteration":19,"passed_time":0.03893455942,"remaining_time":0.5879118473},
{"learn":[0.4328994925],"iteration":20,"passed_time":0.04151708545,"remaining_time":0.5950782248},
{"learn":[0.4307552824],"iteration":21,"passed_time":0.04359919029,"remaining_time":0.594534413},
{"learn":[0.4287166193],"iteration":22,"passed_time":0.04539955595,"remaining_time":0.5901942273},
{"learn":[0.4267041829],"iteration":23,"passed_time":0.04714538688,"remaining_time":0.5853885537},
{"learn":[0.424776583],"iteration":24,"passed_time":0.04883515602,"remaining_time":0.5801616536},
{"learn":[0.4229061411],"iteration":25,"passed_time":0.05050565675,"remaining_time":0.5749874769},
{"learn":[0.4212693293],"iteration":26,"passed_time":0.05219867237,"remaining_time":0.5703188278},
{"learn":[0.4195947808],"iteration":27,"passed_time":0.05416675644,"remaining_time":0.5687509426},
{"learn":[0.4176936779],"iteration":28,"passed_time":0.05638310551,"remaining_time":0.5696637902},
{"learn":[0.4159795637],"iteration":29,"passed_time":0.05932893305,"remaining_time":0.5774682817},
{"learn":[0.4143635351],"iteration":30,"passed_time":0.06124977292,"remaining_time":0.5749575458},
{"learn":[0.4126593224],"iteration":31,"passed_time":0.06291359032,"remaining_time":0.5701544123},
{"learn":[0.411125392],"iteration":32,"passed_time":0.06460534343,"remaining_time":0.5657861894},
{"learn":[0.4096248815],"iteration":33,"passed_time":0.06631336898,"remaining_time":0.5617132431},
{"learn":[0.408093087],"iteration":34,"passed_time":0.06803749663,"remaining_time":0.5579074724},
{"learn":[0.4066901504],"iteration":35,"passed_time":0.07248413227,"remaining_time":0.5758461619},
{"learn":[0.4052529791],"iteration":36,"passed_time":0.0746628526,"remaining_time":0.5751057565},
{"learn":[0.4038841464],"iteration":37,"passed_time":0.07627127355,"remaining_time":0.5700274129},
{"learn":[0.4026330027],"iteration":38,"passed_time":0.07787166449,"remaining_time":0.5650687449},
{"learn":[0.4013309954],"iteration":39,"passed_time":0.0794677165,"remaining_time":0.5602474013},
{"learn":[0.4000897053],"iteration":40,"passed_time":0.08122278613,"remaining_time":0.5566732415},
{"learn":[0.3989169125],"iteration":41,"passed_time":0.0828946095,"remaining_time":0.55263073},
{"learn":[0.3979136367],"iteration":42,"passed_time":0.08483434705,"remaining_time":0.5504368099},
{"learn":[0.3968022777],"iteration":43,"passed_time":0.08662901535,"remaining_time":0.5473378697},
{"learn":[0.3958400841],"iteration":44,"passed_time":0.08827286895,"remaining_time":0.5433685488},
{"learn":[0.3948273629],"iteration":45,"passed_time":0.09062376027,"remaining_time":0.5437425616},
{"learn":[0.3938382921],"iteration":46,"passed_time":0.09229389026,"remaining_time":0.540017443},
{"learn":[0.3929710314],"iteration":47,"passed_time":0.0940549215,"remaining_time":0.5368968436},
{"learn":[0.3920600622],"iteration":48,"passed_time":0.09571704152,"remaining_time":0.5332806599},
{"learn":[0.3912770743],"iteration":49,"passed_time":0.09735114367,"remaining_time":0.5295902216},
{"learn":[0.3903916817],"iteration":50,"passed_time":0.09920839762,"remaining_time":0.5271661913},
{"learn":[0.3895475833],"iteration":51,"passed_time":0.1009334362,"remaining_time":0.5240774574},
{"learn":[0.3886782426],"iteration":52,"passed_time":0.1031861378,"remaining_time":0.523718322},
{"learn":[0.3877665382],"iteration":53,"passed_time":0.105990065,"remaining_time":0.5260247669},
{"learn":[0.3868936277],"iteration":54,"passed_time":0.1077863496,"remaining_time":0.5232537337},
{"learn":[0.3861106011],"iteration":55,"passed_time":0.1094623614,"remaining_time":0.5199462164},
{"learn":[0.385373436],"iteration":56,"passed_time":0.1110668505,"remaining_time":0.5163634276},
{"learn":[0.3845875431],"iteration":57,"passed_time":0.1127125818,"remaining_time":0.5130365793},
{"learn":[0.3838512356],"iteration":58,"passed_time":0.11453713,"remaining_time":0.5105638166},
{"learn":[0.3832042302],"iteration":59,"passed_time":0.1162066885,"remaining_time":0.5074358733},
{"learn":[0.3825188876],"iteration":60,"passed_time":0.1179137825,"remaining_time":0.5045163481},
{"learn":[0.3819147076],"iteration":61,"passed_time":0.1196023994,"remaining_time":0.5015584489},
{"learn":[0.3812131276],"iteration":62,"passed_time":0.1213531902,"remaining_time":0.4988964485},
{"learn":[0.3806220414],"iteration":63,"passed_time":0.1236223505,"remaining_time":0.4983526006},
{"learn":[0.3799540205],"iteration":64,"passed_time":0.1253146585,"remaining_time":0.4954748804},
{"learn":[0.3793498497],"iteration":65,"passed_time":0.1269602395,"remaining_time":0.4924518381},
{"learn":[0.3787951063],"iteration":66,"passed_time":0.1287246475,"remaining_time":0.4899221658},
{"learn":[0.3782761202],"iteration":67,"passed_time":0.1305887743,"remaining_time":0.4877874804},
{"learn":[0.3777764542],"iteration":68,"passed_time":0.1322463595,"remaining_time":0.4849033183},
{"learn":[0.3772517398],"iteration":69,"passed_time":0.133942287,"remaining_time":0.4821922331},
{"learn":[0.3767018959],"iteration":70,"passed_time":0.1357589027,"remaining_time":0.4799364026},
{"learn":[0.3761377261],"iteration":71,"passed_time":0.1374444535,"remaining_time":0.4772376857},
{"learn":[0.3756698732],"iteration":72,"passed_time":0.1398819898,"remaining_time":0.4771317188},
{"learn":[0.3752377881],"iteration":73,"passed_time":0.1417674592,"remaining_time":0.4751125659},
{"learn":[0.3746602691],"iteration":74,"passed_time":0.1437242456,"remaining_time":0.4733318488},
{"learn":[0.3743000119],"iteration":75,"passed_time":0.1453912184,"remaining_time":0.4706084175},
{"learn":[0.3739700341],"iteration":76,"passed_time":0.1471073398,"remaining_time":0.4680688085},
{"learn":[0.3733795718],"iteration":77,"passed_time":0.1488058066,"remaining_time":0.4654950873},
{"learn":[0.3729529853],"iteration":78,"passed_time":0.1504738725,"remaining_time":0.4628500128},
{"learn":[0.3726078928],"iteration":79,"passed_time":0.1521895934,"remaining_time":0.4603735199},
{"learn":[0.3721015376],"iteration":80,"passed_time":0.1540620465,"remaining_time":0.4583821383},
{"learn":[0.3716430593],"iteration":81,"passed_time":0.1560988338,"remaining_time":0.4568746356},
{"learn":[0.3711187901],"iteration":82,"passed_time":0.1577773145,"remaining_time":0.4543226284},
{"learn":[0.3707663656],"iteration":83,"passed_time":0.1597081156,"remaining_time":0.4525063276},
{"learn":[0.370360696],"iteration":84,"passed_time":0.1616934526,"remaining_time":0.4508393915},
{"learn":[0.370084288],"iteration":85,"passed_time":0.1634389028,"remaining_time":0.4485067566},
{"learn":[0.3696161176],"iteration":86,"passed_time":0.1652024004,"remaining_time":0.4462363689},
{"learn":[0.3692088505],"iteration":87,"passed_time":0.1670314859,"remaining_time":0.4441519057},
{"learn":[0.3688311966],"iteration":88,"passed_time":0.1688698613,"remaining_time":0.4420975022},
{"learn":[0.3685612222],"iteration":89,"passed_time":0.1708076948,"remaining_time":0.4403042799},
{"learn":[0.3680290482],"iteration":90,"passed_time":0.1730822903,"remaining_time":0.4393627369},
{"learn":[0.3676715199],"iteration":91,"passed_time":0.1752989901,"remaining_time":0.4382474752},
{"learn":[0.3674257937],"iteration":92,"passed_time":0.1776773018,"remaining_time":0.4375064743},
{"learn":[0.3671410044],"iteration":93,"passed_time":0.1799866162,"remaining_time":0.4365632819},
{"learn":[0.3668884589],"iteration":94,"passed_time":0.1824371422,"remaining_time":0.4359287503},
{"learn":[0.3666678039],"iteration":95,"passed_time":0.184705876,"remaining_time":0.4348284164},
{"learn":[0.3662518765],"iteration":96,"passed_time":0.1871148191,"remaining_time":0.4340292195},
{"learn":[0.3659363202],"iteration":97,"passed_time":0.189542265,"remaining_time":0.4332394629},
{"learn":[0.3654945219],"iteration":98,"passed_time":0.1913912817,"remaining_time":0.4311136951},
{"learn":[0.3651554664],"iteration":99,"passed_time":0.1930651531,"remaining_time":0.42860464},
{"learn":[0.3648607411],"iteration":100,"passed_time":0.1948847712,"remaining_time":0.426431034},
{"learn":[0.3645506309],"iteration":101,"passed_time":0.1966073317,"remaining_time":0.4240550292},
{"learn":[0.3643462278],"iteration":102,"passed_time":0.1983073653,"remaining_time":0.4216438156},
{"learn":[0.3640501706],"iteration":103,"passed_time":0.2000050663,"remaining_time":0.419241389},
{"learn":[0.3637126962],"iteration":104,"passed_time":0.2018136764,"remaining_time":0.4170815979},
{"learn":[0.3635178196],"iteration":105,"passed_time":0.2043014475,"remaining_time":0.4163123836},
{"learn":[0.3632336487],"iteration":106,"passed_time":0.2060635099,"remaining_time":0.4140528471},
{"learn":[0.3628979852],"iteration":107,"passed_time":0.207926392,"remaining_time":0.4120022952},
{"learn":[0.3627548297],"iteration":108,"passed_time":0.2097974448,"remaining_time":0.4099711537},
{"learn":[0.3624282286],"iteration":109,"passed_time":0.211506298,"remaining_time":0.4076303199},
{"learn":[0.3621645488],"iteration":110,"passed_time":0.213147845,"remaining_time":0.4051729307},
{"learn":[0.3616808475],"iteration":111,"passed_time":0.2148512313,"remaining_time":0.4028460588},
{"learn":[0.3614178399],"iteration":112,"passed_time":0.2164975438,"remaining_time":0.4004246607},
{"learn":[0.3611534346],"iteration":113,"passed_time":0.2181838962,"remaining_time":0.3980899158},
{"learn":[0.3609840166],"iteration":114,"passed_time":0.220682147,"remaining_time":0.3972278647},
{"learn":[0.3607052781],"iteration":115,"passed_time":0.2227899296,"remaining_time":0.3956441854},
{"learn":[0.3605128888],"iteration":116,"passed_time":0.2245843978,"remaining_time":0.3935025774},
{"learn":[0.3603005411],"iteration":117,"passed_time":0.2262391071,"remaining_time":0.3911252359},
{"learn":[0.3600472669],"iteration":118,"passed_time":0.2278691872,"remaining_time":0.3887180252},
{"learn":[0.3598880991],"iteration":119,"passed_time":0.2294796783,"remaining_time":0.3862907918},
{"learn":[0.3597868194],"iteration":120,"passed_time":0.2311279547,"remaining_time":0.3839398256},
{"learn":[0.3596115088],"iteration":121,"passed_time":0.2327894174,"remaining_time":0.3816219958},
{"learn":[0.3592821115],"iteration":122,"passed_time":0.2347376717,"remaining_time":0.3797788346},
{"learn":[0.3590999381],"iteration":123,"passed_time":0.2376190478,"remaining_time":0.3794239635},
{"learn":[0.3588376137],"iteration":124,"passed_time":0.2394732299,"remaining_time":0.3774098104},
{"learn":[0.3586782281],"iteration":125,"passed_time":0.241575363,"remaining_time":0.375783898},
{"learn":[0.3584169577],"iteration":126,"passed_time":0.2433363063,"remaining_time":0.3736266121},
{"learn":[0.3582008985],"iteration":127,"passed_time":0.2452787058,"remaining_time":0.3717505384},
{"learn":[0.3580462924],"iteration":128,"passed_time":0.2471158118,"remaining_time":0.3697159045},
{"learn":[0.3578629244],"iteration":129,"passed_time":0.2488241783,"remaining_time":0.3674941711},
{"learn":[0.3576408837],"iteration":130,"passed_time":0.2508246029,"remaining_time":0.3657061004},
{"learn":[0.3574387701],"iteration":131,"passed_time":0.2528542196,"remaining_time":0.3639568313},
{"learn":[0.3571837993],"iteration":132,"passed_time":0.2557123423,"remaining_time":0.363380697},
{"learn":[0.3570025765],"iteration":133,"passed_time":0.2582150924,"remaining_time":0.3622719207},
{"learn":[0.356875032],"iteration":134,"passed_time":0.2605863612,"remaining_time":0.360960367},
{"learn":[0.3566529438],"iteration":135,"passed_time":0.2628994824,"remaining_time":0.3595537039},
{"learn":[0.3565067252],"iteration":136,"passed_time":0.2653526528,"remaining_time":0.3583229253},
{"learn":[0.3563505938],"iteration":137,"passed_time":0.2670163906,"remaining_time":0.3560218541},
{"learn":[0.3560387435],"iteration":138,"passed_time":0.2690456169,"remaining_time":0.3542111359},
{"learn":[0.3557729006],"iteration":139,"passed_time":0.2717271795,"remaining_time":0.3532453334},
{"learn":[0.3555663471],"iteration":140,"passed_time":0.2740026705,"remaining_time":0.3517339245},
{"learn":[0.3552777357],"iteration":141,"passed_time":0.2759948586,"remaining_time":0.3498526377},
{"learn":[0.3550830128],"iteration":142,"passed_time":0.2777151987,"remaining_time":0.3476295145},
{"learn":[0.3548706768],"iteration":143,"passed_time":0.2794067454,"remaining_time":0.3453777825},
{"learn":[0.3545216844],"iteration":144,"passed_time":0.2813001566,"remaining_time":0.3433801912},
{"learn":[0.3543750459],"iteration":145,"passed_time":0.2830976044,"remaining_time":0.3412683451},
{"learn":[0.3542271666],"iteration":146,"passed_time":0.2851087403,"remaining_time":0.3394151671},
{"learn":[0.3540278641],"iteration":147,"passed_time":0.2878962119,"remaining_time":0.3384725734},
{"learn":[0.3539037978],"iteration":148,"passed_time":0.2895373941,"remaining_time":0.3361742898},
{"learn":[0.3537534952],"iteration":149,"passed_time":0.2913237859,"remaining_time":0.3340512745},
{"learn":[0.3534980943],"iteration":150,"passed_time":0.2933352327,"remaining_time":0.3321875815},
{"learn":[0.353301469],"iteration":151,"passed_time":0.2953310452,"remaining_time":0.3303044585},
{"learn":[0.3531202722],"iteration":152,"passed_time":0.2969972079,"remaining_time":0.3280557394},
{"learn":[0.3528990128],"iteration":153,"passed_time":0.2988277371,"remaining_time":0.325993895},
{"learn":[0.3527366195],"iteration":154,"passed_time":0.3008139648,"remaining_time":0.3241027879},
{"learn":[0.35261004],"iteration":155,"passed_time":0.3032550013,"remaining_time":0.3226944244},
{"learn":[0.3524831156],"iteration":156,"passed_time":0.3049409477,"remaining_time":0.3204793399},
{"learn":[0.3523805317],"iteration":157,"passed_time":0.3066768539,"remaining_time":0.3183228104},
{"learn":[0.3522573966],"iteration":158,"passed_time":0.3083783313,"remaining_time":0.3161362767},
{"learn":[0.352201547],"iteration":159,"passed_time":0.310511179,"remaining_time":0.3143925688},
{"learn":[0.3520758874],"iteration":160,"passed_time":0.3121937679,"remaining_time":0.3121937679},
{"learn":[0.3517765202],"iteration":161,"passed_time":0.3139603902,"remaining_time":0.310084336},
{"learn":[0.3515385576],"iteration":162,"passed_time":0.315666512,"remaining_time":0.3079200945},
{"learn":[0.3513421506],"iteration":163,"passed_time":0.3174291063,"remaining_time":0.3058158463},
{"learn":[0.3512528623],"iteration":164,"passed_time":0.3201365855,"remaining_time":0.3046148117},
{"learn":[0.3511083548],"iteration":165,"passed_time":0.3218880766,"remaining_time":0.3024972286},
{"learn":[0.3509600895],"iteration":166,"passed_time":0.3235657516,"remaining_time":0.300315518},
{"learn":[0.3507625934],"iteration":167,"passed_time":0.3255791675,"remaining_time":0.2984475702},
{"learn":[0.3505643962],"iteration":168,"passed_time":0.3273633998,"remaining_time":0.2963704152},
{"learn":[0.3503142689],"iteration":169,"passed_time":0.3291187938,"remaining_time":0.2942709215},
{"learn":[0.3501241497],"iteration":170,"passed_time":0.3307968393,"remaining_time":0.2921071505},
{"learn":[0.3499423513],"iteration":171,"passed_time":0.3325390032,"remaining_time":0.2900049447},
{"learn":[0.3496982714],"iteration":172,"passed_time":0.334524983,"remaining_time":0.2881168928},
{"learn":[0.349573537],"iteration":173,"passed_time":0.3368554055,"remaining_time":0.2865206897},
{"learn":[0.3494350589],"iteration":174,"passed_time":0.3386116208,"remaining_time":0.2844337615},
{"learn":[0.3493071823],"iteration":175,"passed_time":0.3404173626,"remaining_time":0.2823916758},
{"learn":[0.3491476172],"iteration":176,"passed_time":0.3423852351,"remaining_time":0.2804850796},
{"learn":[0.3489597875],"iteration":177,"passed_time":0.3440343933,"remaining_time":0.2783199586},
{"learn":[0.348781419],"iteration":178,"passed_time":0.3457457816,"remaining_time":0.2762103171},
{"learn":[0.3487030836],"iteration":179,"passed_time":0.3474337571,"remaining_time":0.2740866306},
{"learn":[0.3484985641],"iteration":180,"passed_time":0.3491904197,"remaining_time":0.2720212661},
{"learn":[0.3483234331],"iteration":181,"passed_time":0.3510662904,"remaining_time":0.2700509926},
{"learn":[0.3480687122],"iteration":182,"passed_time":0.3533225986,"remaining_time":0.268370717},
{"learn":[0.3479527258],"iteration":183,"passed_time":0.3550912104,"remaining_time":0.2663184078},
{"learn":[0.3477555462],"iteration":184,"passed_time":0.3568158837,"remaining_time":0.2642366274},
{"learn":[0.347657427],"iteration":185,"passed_time":0.3588021257,"remaining_time":0.2623499414},
{"learn":[0.3474075117],"iteration":186,"passed_time":0.3605897282,"remaining_time":0.2603187877},
{"learn":[0.3472407763],"iteration":187,"passed_time":0.3623118118,"remaining_time":0.2582435254},
{"learn":[0.3470737199],"iteration":188,"passed_time":0.3639803626,"remaining_time":0.2561343292},
{"learn":[0.3470089086],"iteration":189,"passed_time":0.3655790301,"remaining_time":0.2539812209},
{"learn":[0.3468511278],"iteration":190,"passed_time":0.3677144945,"remaining_time":0.2522020878},
{"learn":[0.3467265619],"iteration":191,"passed_time":0.36951108,"remaining_time":0.2501897938},
{"learn":[0.3464716195],"iteration":192,"passed_time":0.3713729022,"remaining_time":0.2482233388},
{"learn":[0.3462865821],"iteration":193,"passed_time":0.3732055571,"remaining_time":0.2462387181},
{"learn":[0.3460350029],"iteration":194,"passed_time":0.3749195197,"remaining_time":0.2441783538},
{"learn":[0.3459098634],"iteration":195,"passed_time":0.3766164872,"remaining_time":0.2421105989},
{"learn":[0.3456305143],"iteration":196,"passed_time":0.3783953247,"remaining_time":0.2400985563},
{"learn":[0.3454774656],"iteration":197,"passed_time":0.3800617565,"remaining_time":0.2380184738},
{"learn":[0.3454083423],"iteration":198,"passed_time":0.3817695015,"remaining_time":0.2359680838},
{"learn":[0.3453241325],"iteration":199,"passed_time":0.3843822509,"remaining_time":0.2344731731},
{"learn":[0.3452412913],"iteration":200,"passed_time":0.3862141595,"remaining_time":0.2324970811},
{"learn":[0.3449589519],"iteration":201,"passed_time":0.3879825494,"remaining_time":0.2304846828},
{"learn":[0.3448181867],"iteration":202,"passed_time":0.3897273382,"remaining_time":0.2284608534},
{"learn":[0.3447499139],"iteration":203,"passed_time":0.391331132,"remaining_time":0.2263582038},
{"learn":[0.3445278254],"iteration":204,"passed_time":0.3932273845,"remaining_time":0.2244273365},
{"learn":[0.3444411266],"iteration":205,"passed_time":0.3949531377,"remaining_time":0.222400796},
{"learn":[0.3442041645],"iteration":206,"passed_time":0.3965882178,"remaining_time":0.2203267877},
{"learn":[0.3440755459],"iteration":207,"passed_time":0.3983856817,"remaining_time":0.2183459986},
{"learn":[0.3439453824],"iteration":208,"passed_time":0.4009881815,"remaining_time":0.2168022226},
{"learn":[0.3438444869],"iteration":209,"passed_time":0.4029805031,"remaining_time":0.214922935},
{"learn":[0.3436181127],"iteration":210,"passed_time":0.4049009822,"remaining_time":0.2130047821},
{"learn":[0.3434488458],"iteration":211,"passed_time":0.4066704904,"remaining_time":0.2110082733},
{"learn":[0.3431785708],"iteration":212,"passed_time":0.4083414219,"remaining_time":0.2089634507},
{"learn":[0.3430098823],"iteration":213,"passed_time":0.4099991532,"remaining_time":0.2069154605},
{"learn":[0.3428854865],"iteration":214,"passed_time":0.4117382347,"remaining_time":0.2049115866},
{"learn":[0.3428083837],"iteration":215,"passed_time":0.4134283746,"remaining_time":0.2028861468},
{"learn":[0.3426193903],"iteration":216,"passed_time":0.415195504,"remaining_time":0.2009010503},
{"learn":[0.34247476],"iteration":217,"passed_time":0.4181450097,"remaining_time":0.199482023},
{"learn":[0.3423313797],"iteration":218,"passed_time":0.4198687354,"remaining_time":0.1974725103},
{"learn":[0.3422478527],"iteration":219,"passed_time":0.4215752943,"remaining_time":0.1954576365},
{"learn":[0.3420788081],"iteration":220,"passed_time":0.4232797264,"remaining_time":0.1934445808},
{"learn":[0.3419477688],"iteration":221,"passed_time":0.4249651672,"remaining_time":0.191425751},
{"learn":[0.3416810581],"iteration":222,"passed_time":0.4266568061,"remaining_time":0.1894126628},
{"learn":[0.3416065814],"iteration":223,"passed_time":0.4283213489,"remaining_time":0.1873905902},
{"learn":[0.3414179022],"iteration":224,"passed_time":0.4299964989,"remaining_time":0.1853762684},
{"learn":[0.3412599215],"iteration":225,"passed_time":0.4319273548,"remaining_time":0.1834735666},
{"learn":[0.3411035575],"iteration":226,"passed_time":0.4345606489,"remaining_time":0.1818645887},
{"learn":[0.3409127672],"iteration":227,"passed_time":0.4362245865,"remaining_time":0.1798469787},
{"learn":[0.340740142],"iteration":228,"passed_time":0.4379785437,"remaining_time":0.1778690155},
{"learn":[0.3406058233],"iteration":229,"passed_time":0.4396922007,"remaining_time":0.1758768803},
{"learn":[0.34037767],"iteration":230,"passed_time":0.4414565984,"remaining_time":0.1739071448},
{"learn":[0.340214279],"iteration":231,"passed_time":0.4430986627,"remaining_time":0.1718917226},
{"learn":[0.3400808264],"iteration":232,"passed_time":0.4448031412,"remaining_time":0.1699033458},
{"learn":[0.3398931513],"iteration":233,"passed_time":0.4467505841,"remaining_time":0.1680087667},
{"learn":[0.3397407169],"iteration":234,"passed_time":0.4489073544,"remaining_time":0.1661912333},
{"learn":[0.3396536899],"iteration":235,"passed_time":0.4513790886,"remaining_time":0.1644856001},
{"learn":[0.3395054117],"iteration":236,"passed_time":0.4529991889,"remaining_time":0.1624680635},
{"learn":[0.3392766352],"iteration":237,"passed_time":0.4547269186,"remaining_time":0.1604918536},
{"learn":[0.3391485219],"iteration":238,"passed_time":0.456364619,"remaining_time":0.1584864577},
{"learn":[0.3389461037],"iteration":239,"passed_time":0.4580574643,"remaining_time":0.156502967},
{"learn":[0.3388531336],"iteration":240,"passed_time":0.4597272877,"remaining_time":0.1545141506},
{"learn":[0.338700283],"iteration":241,"passed_time":0.4645718771,"remaining_time":0.15357748},
{"learn":[0.3385245151],"iteration":242,"passed_time":0.4672122075,"remaining_time":0.1518920345},
{"learn":[0.3384558567],"iteration":243,"passed_time":0.4689255336,"remaining_time":0.1499024247},
{"learn":[0.3383381225],"iteration":244,"passed_time":0.4705429425,"remaining_time":0.1478849248},
{"learn":[0.3380727028],"iteration":245,"passed_time":0.47222686,"remaining_time":0.145891225},
{"learn":[0.3379311003],"iteration":246,"passed_time":0.4739428411,"remaining_time":0.1439097696},
{"learn":[0.3377810759],"iteration":247,"passed_time":0.4757101048,"remaining_time":0.1419457571},
{"learn":[0.3377224546],"iteration":248,"passed_time":0.477605384,"remaining_time":0.1400208555},
{"learn":[0.3375582476],"iteration":249,"passed_time":0.4795751491,"remaining_time":0.1381176429},
{"learn":[0.3372818696],"iteration":250,"passed_time":0.4814832659,"remaining_time":0.1361964617},
{"learn":[0.3371556214],"iteration":251,"passed_time":0.4837600314,"remaining_time":0.1343777865},
{"learn":[0.3370844261],"iteration":252,"passed_time":0.4854665039,"remaining_time":0.1323999556},
{"learn":[0.3369859025],"iteration":253,"passed_time":0.48718485,"remaining_time":0.1304274402},
{"learn":[0.3369330976],"iteration":254,"passed_time":0.4888147237,"remaining_time":0.1284336725},
{"learn":[0.3368166468],"iteration":255,"passed_time":0.49043788,"remaining_time":0.126441016},
{"learn":[0.3366020557],"iteration":256,"passed_time":0.4925697006,"remaining_time":0.1245798854},
{"learn":[0.3365131057],"iteration":257,"passed_time":0.4944420446,"remaining_time":0.1226522901},
{"learn":[0.3364820905],"iteration":258,"passed_time":0.4965897356,"remaining_time":0.1207920979},
{"learn":[0.3362044483],"iteration":259,"passed_time":0.4991156488,"remaining_time":0.1190198855},
{"learn":[0.336034236],"iteration":260,"passed_time":0.5008816434,"remaining_time":0.1170642921},
{"learn":[0.3356736425],"iteration":261,"passed_time":0.5025929815,"remaining_time":0.1150976294},
{"learn":[0.3356085962],"iteration":262,"passed_time":0.504254324,"remaining_time":0.1131216925},
{"learn":[0.3354142474],"iteration":263,"passed_time":0.5060484343,"remaining_time":0.1111773075},
{"learn":[0.3352858656],"iteration":264,"passed_time":0.5078296627,"remaining_time":0.1092312859},
{"learn":[0.3350557575],"iteration":265,"passed_time":0.5095840507,"remaining_time":0.1072808528},
{"learn":[0.33498715],"iteration":266,"passed_time":0.5114106827,"remaining_time":0.1053467698},
{"learn":[0.3348633741],"iteration":267,"passed_time":0.5131267884,"remaining_time":0.1033912185},
{"learn":[0.334724778],"iteration":268,"passed_time":0.5156493294,"remaining_time":0.1015963363},
{"learn":[0.3344823663],"iteration":269,"passed_time":0.5173588364,"remaining_time":0.09963947961},
{"learn":[0.3342654605],"iteration":270,"passed_time":0.519008676,"remaining_time":0.09767321946},
{"learn":[0.3340734781],"iteration":271,"passed_time":0.5206909167,"remaining_time":0.09571524203},
{"learn":[0.3339234203],"iteration":272,"passed_time":0.5226400063,"remaining_time":0.09380718062},
{"learn":[0.3337891134],"iteration":273,"passed_time":0.5245059776,"remaining_time":0.09188425885},
{"learn":[0.3336951548],"iteration":274,"passed_time":0.5261750555,"remaining_time":0.0899281004},
{"learn":[0.3336550162],"iteration":275,"passed_time":0.5278703949,"remaining_time":0.08797839915},
{"learn":[0.3335021053],"iteration":276,"passed_time":0.5295135211,"remaining_time":0.08602205216},
{"learn":[0.3333067922],"iteration":277,"passed_time":0.5328836105,"remaining_time":0.08434129087},
{"learn":[0.333241033],"iteration":278,"passed_time":0.5362268925,"remaining_time":0.08264428809},
{"learn":[0.3330938365],"iteration":279,"passed_time":0.5379899318,"remaining_time":0.08069848976},
{"learn":[0.3330527272],"iteration":280,"passed_time":0.5397613497,"remaining_time":0.07875521472},
{"learn":[0.3328182064],"iteration":281,"passed_time":0.5413925561,"remaining_time":0.07679327037},
{"learn":[0.3327597156],"iteration":282,"passed_time":0.5431295093,"remaining_time":0.07484823626},
{"learn":[0.3326087741],"iteration":283,"passed_time":0.544984706,"remaining_time":0.07292048883},
{"learn":[0.3322950338],"iteration":284,"passed_time":0.5469381933,"remaining_time":0.07100601105},
{"learn":[0.3321207379],"iteration":285,"passed_time":0.5493028958,"remaining_time":0.06914302185},
{"learn":[0.3320450444],"iteration":286,"passed_time":0.55128421,"remaining_time":0.06722978171},
{"learn":[0.3318679127],"iteration":287,"passed_time":0.5531995383,"remaining_time":0.06530827883},
{"learn":[0.3316526269],"iteration":288,"passed_time":0.5553531823,"remaining_time":0.0634140312},
{"learn":[0.3314250543],"iteration":289,"passed_time":0.5572625385,"remaining_time":0.06149103873},
{"learn":[0.3313253657],"iteration":290,"passed_time":0.5590573969,"remaining_time":0.05955594262},
{"learn":[0.3312500351],"iteration":291,"passed_time":0.5606376476,"remaining_time":0.05759975832},
{"learn":[0.3311443547],"iteration":292,"passed_time":0.5623241603,"remaining_time":0.0556566575},
{"learn":[0.3308763558],"iteration":293,"passed_time":0.5649587043,"remaining_time":0.05380559089},
{"learn":[0.3307247543],"iteration":294,"passed_time":0.5670167635,"remaining_time":0.05189644954},
{"learn":[0.3305753859],"iteration":295,"passed_time":0.5687101433,"remaining_time":0.04995426934},
{"learn":[0.3304920962],"iteration":296,"passed_time":0.5705717559,"remaining_time":0.04802792558},
{"learn":[0.3303545297],"iteration":297,"passed_time":0.5722568048,"remaining_time":0.04608779636},
{"learn":[0.330241315],"iteration":298,"passed_time":0.5741112423,"remaining_time":0.04416240325},
{"learn":[0.330148399],"iteration":299,"passed_time":0.5760533145,"remaining_time":0.04224390973},
{"learn":[0.3300860095],"iteration":300,"passed_time":0.5777520715,"remaining_time":0.04030828406},
{"learn":[0.3299261367],"iteration":301,"passed_time":0.5797490641,"remaining_time":0.03839397775},
{"learn":[0.3297748456],"iteration":302,"passed_time":0.5821826363,"remaining_time":0.03650650194},
{"learn":[0.3296688658],"iteration":303,"passed_time":0.5839239934,"remaining_time":0.03457444698},
{"learn":[0.3294969732],"iteration":304,"passed_time":0.5857988516,"remaining_time":0.03265108353},
{"learn":[0.3293382974],"iteration":305,"passed_time":0.5877135633,"remaining_time":0.03073012096},
{"learn":[0.3291620884],"iteration":306,"passed_time":0.5893816492,"remaining_time":0.02879714898},
{"learn":[0.3290946454],"iteration":307,"passed_time":0.5910391901,"remaining_time":0.02686541773},
{"learn":[0.32896678],"iteration":308,"passed_time":0.5927103962,"remaining_time":0.02493603609},
{"learn":[0.3288739053],"iteration":309,"passed_time":0.5944497642,"remaining_time":0.02301095862},
{"learn":[0.3287692276],"iteration":310,"passed_time":0.5967370007,"remaining_time":0.0211064534},
{"learn":[0.3286193185],"iteration":311,"passed_time":0.598683636,"remaining_time":0.01918857808},
{"learn":[0.3283364212],"iteration":312,"passed_time":0.6005142419,"remaining_time":0.01726718267},
{"learn":[0.3281592988],"iteration":313,"passed_time":0.6024280618,"remaining_time":0.01534848565},
{"learn":[0.3280887128],"iteration":314,"passed_time":0.6041868385,"remaining_time":0.01342637419},
{"learn":[0.3279187827],"iteration":315,"passed_time":0.6058939022,"remaining_time":0.0115043146},
{"learn":[0.3277838276],"iteration":316,"passed_time":0.6075845931,"remaining_time":0.009583353204},
{"learn":[0.3275927341],"iteration":317,"passed_time":0.6092655547,"remaining_time":0.00766371767},
{"learn":[0.3274830789],"iteration":318,"passed_time":0.6111457095,"remaining_time":0.005747451813},
{"learn":[0.3273317339],"iteration":319,"passed_time":0.6132127849,"remaining_time":0.003832579906},
{"learn":[0.3271536373],"iteration":320,"passed_time":0.6151852486,"remaining_time":0.001916464949},
{"learn":[0.3269721468],"iteration":321,"passed_time":0.6174610754,"remaining_time":0}
]}